<?xml version="1.0" encoding="utf-8" ?>
<dwsync>
<file name=".gitattributes" server="ftp.reinaldopinto.esy.es//public_html/" local="131334132255633061" remote="131339174400000000" Dst="0" />
<file name=".gitignore" server="ftp.reinaldopinto.esy.es//public_html/" local="131334132255723137" remote="131339174400000000" Dst="0" />
<file name="fale-conosco.html" server="ftp.reinaldopinto.esy.es//public_html/" local="131336787056191685" remote="131339174400000000" Dst="0" />
<file name="fotos.html" server="ftp.reinaldopinto.esy.es//public_html/" local="131339039518309409" remote="131339174400000000" Dst="0" />
<file name="google-glass.html" server="ftp.reinaldopinto.esy.es//public_html/" local="131339001068408411" remote="131339174400000000" Dst="0" />
<file name="index.html" server="ftp.reinaldopinto.esy.es//public_html/" local="131336770440403601" remote="131339174400000000" Dst="0" />
<file name="multimidia.html" server="ftp.reinaldopinto.esy.es//public_html/" local="131336787057992948" remote="131339174400000000" Dst="0" />
<file name="specs.html" server="ftp.reinaldopinto.esy.es//public_html/" local="131339023833902480" remote="131339174400000000" Dst="0" />
<file name="testejs01.html" server="ftp.reinaldopinto.esy.es//public_html/" local="131336173759243704" remote="131339174400000000" Dst="0" />
<file name="testejs02.html" server="ftp.reinaldopinto.esy.es//public_html/" local="131336728022037027" remote="131339174400000000" Dst="0" />
<file name="testejs03.html" server="ftp.reinaldopinto.esy.es//public_html/" local="131336731799517506" remote="131339174400000000" Dst="0" />
<file name=".htaccess" server="ftp.reinaldopinto.esy.es//public_html/" local="131315629200000000" remote="131315629200000000" Dst="0" />
</dwsync>